{
  "usad_score:critical:threshold": {
    "kind": "threshold",
    "threshold": 0.9916556288474411,
    "fa_budget_per_hour": 2.0,
    "calibration_fa_per_hour": 1.954397394136808
  },
  "usad_score:critical:k_of_n": {
    "kind": "k_of_n",
    "k": 3,
    "n": 5,
    "threshold": 0.9909445367294204,
    "fa_budget_per_hour": 2.0,
    "calibration_fa_per_hour": 1.954397394136808
  },
  "usad_score:critical:cusum": {
    "kind": "cusum",
    "mu_normal": 0.18143465223970856,
    "sigma_normal": 1.9995690050909645,
    "k": 0.5,
    "h": 121.6875,
    "refractory_seconds": 30.0,
    "stride_seconds": 1.0,
    "bootstrap_hours": 200.0,
    "fa_budget_per_hour": 2.0,
    "calibration_fa_per_hour": 2.0
  },
  "usad_score:advisory:threshold": {
    "kind": "threshold",
    "threshold": 0.9698133833127319,
    "fa_budget_per_hour": 12.0,
    "calibration_fa_per_hour": 11.726384364820849
  },
  "usad_score:advisory:k_of_n": {
    "kind": "k_of_n",
    "k": 3,
    "n": 5,
    "threshold": 0.9664553206692307,
    "fa_budget_per_hour": 12.0,
    "calibration_fa_per_hour": 11.92182410423453
  },
  "usad_score:advisory:cusum": {
    "kind": "cusum",
    "mu_normal": 0.18143465223970856,
    "sigma_normal": 1.9995690050909645,
    "k": 0.5,
    "h": 25.7109375,
    "refractory_seconds": 30.0,
    "stride_seconds": 1.0,
    "bootstrap_hours": 200.0,
    "fa_budget_per_hour": 12.0,
    "calibration_fa_per_hour": 12.0
  },
  "usad_ml14_fusion:critical:threshold": {
    "kind": "threshold",
    "threshold": 0.9999970869091523,
    "fa_budget_per_hour": 2.0,
    "calibration_fa_per_hour": 0.0
  },
  "usad_ml14_fusion:critical:k_of_n": {
    "kind": "k_of_n",
    "k": 2,
    "n": 3,
    "threshold": 0.9999970869091523,
    "fa_budget_per_hour": 2.0,
    "calibration_fa_per_hour": 0.0
  },
  "usad_ml14_fusion:critical:cusum": {
    "kind": "cusum",
    "mu_normal": 6.363199336643825,
    "sigma_normal": 3.5237617666098666,
    "k": 0.5,
    "h": 72.75,
    "refractory_seconds": 30.0,
    "stride_seconds": 1.0,
    "bootstrap_hours": 200.0,
    "fa_budget_per_hour": 2.0,
    "calibration_fa_per_hour": 2.0
  },
  "usad_ml14_fusion:advisory:threshold": {
    "kind": "threshold",
    "threshold": 0.9999970869091523,
    "fa_budget_per_hour": 12.0,
    "calibration_fa_per_hour": 0.0
  },
  "usad_ml14_fusion:advisory:k_of_n": {
    "kind": "k_of_n",
    "k": 2,
    "n": 3,
    "threshold": 0.9999970869091523,
    "fa_budget_per_hour": 12.0,
    "calibration_fa_per_hour": 0.0
  },
  "usad_ml14_fusion:advisory:cusum": {
    "kind": "cusum",
    "mu_normal": 6.363199336643825,
    "sigma_normal": 3.5237617666098666,
    "k": 0.5,
    "h": 28.234375,
    "refractory_seconds": 30.0,
    "stride_seconds": 1.0,
    "bootstrap_hours": 200.0,
    "fa_budget_per_hour": 12.0,
    "calibration_fa_per_hour": 11.97
  },
  "usad_itki_fusion:critical:threshold": {
    "kind": "threshold",
    "threshold": 0.999777225989019,
    "fa_budget_per_hour": 2.0,
    "calibration_fa_per_hour": 1.3680781758957656
  },
  "usad_itki_fusion:critical:k_of_n": {
    "kind": "k_of_n",
    "k": 3,
    "n": 5,
    "threshold": 0.9970238205697292,
    "fa_budget_per_hour": 2.0,
    "calibration_fa_per_hour": 1.954397394136808
  },
  "usad_itki_fusion:critical:cusum": {
    "kind": "cusum",
    "mu_normal": 1.046150529883646,
    "sigma_normal": 1.819453296806175,
    "k": 0.5,
    "h": 104.5625,
    "refractory_seconds": 30.0,
    "stride_seconds": 1.0,
    "bootstrap_hours": 200.0,
    "fa_budget_per_hour": 2.0,
    "calibration_fa_per_hour": 2.0
  },
  "usad_itki_fusion:advisory:threshold": {
    "kind": "threshold",
    "threshold": 0.999777225989019,
    "fa_budget_per_hour": 12.0,
    "calibration_fa_per_hour": 1.3680781758957656
  },
  "usad_itki_fusion:advisory:k_of_n": {
    "kind": "k_of_n",
    "k": 2,
    "n": 3,
    "threshold": 0.9908619225739739,
    "fa_budget_per_hour": 12.0,
    "calibration_fa_per_hour": 9.576547231270359
  },
  "usad_itki_fusion:advisory:cusum": {
    "kind": "cusum",
    "mu_normal": 1.046150529883646,
    "sigma_normal": 1.819453296806175,
    "k": 0.5,
    "h": 19.8203125,
    "refractory_seconds": 30.0,
    "stride_seconds": 1.0,
    "bootstrap_hours": 200.0,
    "fa_budget_per_hour": 12.0,
    "calibration_fa_per_hour": 12.0
  }
}